krait/introspect.py
krait/io.py
krait/types.py
krait/logging.py
krait/package.py
krait/path.py
krait/py.typed
krait/signal.py
krait/signal.pyi
krait_kit-25.6.0.dist-info/METADATA
krait_kit-25.6.0.dist-info/WHEEL
krait_kit-25.6.0.dist-info/entry_points.txt
krait_kit-25.6.0.dist-info/RECORD
